src/__init__.py
src/sql_editor.py
src/file_browser/FileHunter.py
src/file_browser/__init__.py
src/html/__init__.py
src/images/32x32.png
src/images/48x48.png
src/images/AppEngine-16.png
src/images/AppEngine-32.png
src/images/AppEngine-48.png
src/images/AppEngine-64.png
src/images/Egit-0.9-synchronize-conflict-add.png
src/images/Egit-0.9-synchronize-conflict-delete.png
src/images/Egit-0.9-synchronize-conflict-modify.png
src/images/Egit-0.9-synchronize-incoming-add.png
src/images/Egit-0.9-synchronize-incoming-change.png
src/images/Egit-0.9-synchronize-incoming-deletion.png
src/images/Egit-0.9-synchronize-navigation.png
src/images/Egit-0.9-synchronize-outgoing-add.png
src/images/Egit-0.9-synchronize-outgoing-change.png
src/images/Egit-0.9-synchronize-outgoing-delete.png
src/images/Opal_database.png
src/images/Polarion.png
src/images/ResolvedConflicts.png
src/images/Subversive.png
src/images/Subversive_hover.png
src/images/UserAccount.png
src/images/WTP_icon_x32_v2.png
src/images/__init__.py
src/images/abc.png
src/images/about.png
src/images/accept.png
src/images/action-item-favorites.png
src/images/action-item-login.png
src/images/action-item-update.png
src/images/action-item-warning.png
src/images/action.png
src/images/add.png
src/images/add_as_source_folder.png
src/images/add_att.png
src/images/add_correction.png
src/images/add_linked_source_to_buildpath.png
src/images/add_repository.png
src/images/add_snippet.png
src/images/addlibrary_wiz.png
src/images/addsrcloc_wiz.png
src/images/addtoworkset.png
src/images/admin.png
src/images/af.png
src/images/aleft.png
src/images/all_instances.png
src/images/all_references.png
src/images/alphab_sort_co.png
src/images/ancestorpane_co.png
src/images/annotate.png
src/images/annotated-tag.png
src/images/ant.png
src/images/ant_buildfile.png
src/images/ant_view.png
src/images/any.png
src/images/apache.png
src/images/apidocs.png
src/images/argument.png
src/images/aright.png
src/images/arrangeselected.png
src/images/array.png
sql_editor-0.0.5.dist-info/LICENSE
sql_editor-0.0.5.dist-info/METADATA
sql_editor-0.0.5.dist-info/WHEEL
sql_editor-0.0.5.dist-info/entry_points.txt
sql_editor-0.0.5.dist-info/top_level.txt
sql_editor-0.0.5.dist-info/RECORD
