Metadata-Version: 2.1
Name: sql-editor
Version: 0.0.5
Summary: A graphic SQLite Editor in Python
Home-page: https://github.com/struts2spring/sql-editor
Author: Vijay
Author-email: certifyexam0@gmail.com
License: UNKNOWN
Keywords: sqlite,gui,wxpython,sql
Platform: UNKNOWN
Classifier: Development Status :: 5 - Production/Stable
Classifier: Environment :: Console
Classifier: Intended Audience :: Education
Classifier: License :: OSI Approved :: MIT License
Classifier: Operating System :: OS Independent
Classifier: Programming Language :: Python
Classifier: Programming Language :: Python :: 3
Classifier: Programming Language :: Python :: 3.6
Classifier: Topic :: Scientific/Engineering :: Information Analysis
Requires-Python: >=3
Requires-Dist: pypubsub (==4.0.0)
Requires-Dist: six (==1.11.0)
Requires-Dist: wxpython (==4.0.3)
Requires-Dist: sqlparse
